pageql/__init__.py
pageql/cli.py
pageql/client_script.py
pageql/database.py
pageql/http_utils.py
pageql/join.py
pageql/jws_utils.py
pageql/pageql.py
pageql/pageql_async.py
pageql/pageqlapp.py
pageql/params.py
pageql/parser.py
pageql/reactive.py
pageql/reactive_sql.py
pageql/render_context.py
pageql/static/htmx.min.js
pageql-0.2.2.dist-info/METADATA
pageql-0.2.2.dist-info/WHEEL
pageql-0.2.2.dist-info/entry_points.txt
pageql-0.2.2.dist-info/licenses/LICENSE
pageql-0.2.2.dist-info/RECORD
