Metadata-Version: 2.4
Name: pageql
Version: 0.2.2
Summary: A template language for embedding SQL inside HTML directly
Project-URL: Homepage, https://pageql.dev/
Project-URL: GitHub Repository, https://github.com/adamritter/pageql
Project-URL: Issues, https://github.com/adamritter/pageql/issues
Author: adamritter
License-Expression: MIT
License-File: LICENSE
Classifier: License :: OSI Approved :: MIT License
Classifier: Operating System :: OS Independent
Classifier: Programming Language :: Python :: 3
Requires-Python: >=3.7
Requires-Dist: authlib
Requires-Dist: joserfc
Requires-Dist: sqlglot
Requires-Dist: uvicorn[standard]
Requires-Dist: watchfiles
Provides-Extra: dev
Requires-Dist: pytest; extra == 'dev'
